cdflib/CDFLeapSeconds.txt
cdflib/__init__.py
cdflib/_gzip_wrapper.py
cdflib/_version.py
cdflib/cdfread.py
cdflib/cdfwrite.py
cdflib/dataclasses.py
cdflib/epochs.py
cdflib/epochs_astropy.py
cdflib/logging.py
cdflib/s3.py
cdflib/utils.py
cdflib/xarray/__init__.py
cdflib/xarray/cdf_to_xarray.py
cdflib/xarray/xarray_to_cdf.py
cdflib-1.3.8.dist-info/licenses/LICENSE
cdflib-1.3.8.dist-info/METADATA
cdflib-1.3.8.dist-info/WHEEL
cdflib-1.3.8.dist-info/top_level.txt
cdflib-1.3.8.dist-info/RECORD
