Metadata-Version: 2.4
Name: cdflib
Version: 1.3.8
Summary: A python CDF reader toolkit
Author-email: Bryan Harter <harter@lasp.colorado.edu>
License: MIT License
Project-URL: Homepage, https://github.com/lasp/cdflib
Keywords: CDF,maven,lasp,PDS,GSFC
Classifier: Development Status :: 5 - Production/Stable
Classifier: Environment :: Console
Classifier: Intended Audience :: Science/Research
Classifier: Operating System :: OS Independent
Classifier: Programming Language :: Python :: 3.9
Classifier: Programming Language :: Python :: 3.10
Classifier: Programming Language :: Python :: 3.11
Classifier: Programming Language :: Python :: 3.12
Classifier: Programming Language :: Python :: 3.13
Classifier: Programming Language :: Python :: 3 :: Only
Classifier: Topic :: Utilities
Requires-Python: >=3.9
License-File: LICENSE
Requires-Dist: numpy>=1.21
Provides-Extra: tests
Requires-Dist: astropy; extra == "tests"
Requires-Dist: hypothesis; extra == "tests"
Requires-Dist: pytest>=3.9; extra == "tests"
Requires-Dist: pytest-cov; extra == "tests"
Requires-Dist: pytest-remotedata; extra == "tests"
Requires-Dist: xarray; extra == "tests"
Requires-Dist: h5netcdf; extra == "tests"
Requires-Dist: netcdf4; extra == "tests"
Requires-Dist: pooch; extra == "tests"
Provides-Extra: docs
Requires-Dist: mkdocs; extra == "docs"
Requires-Dist: mkdocs-material; extra == "docs"
Requires-Dist: mkdocstrings[python]; extra == "docs"
Provides-Extra: dev
Requires-Dist: ipython; extra == "dev"
Requires-Dist: pre-commit; extra == "dev"
Requires-Dist: matplotlib; extra == "dev"
Dynamic: license-file
